staticvar/__init__.py
staticvar/exceptions.py
staticvar/staticvar.py
staticvar/utils.py
staticvar-0.1.0.dist-info/LICENSE.txt
staticvar-0.1.0.dist-info/METADATA
staticvar-0.1.0.dist-info/WHEEL
staticvar-0.1.0.dist-info/RECORD
