Metadata-Version: 2.1
Name: staticvar
Version: 0.1.0
Summary: The horrors of C Static variables for Python, with Python.
Home-page: https://github.com/AbdelRahmanRahal/staticvar
License: MIT
Keywords: staticvar,static variable,static
Author: AbdelRahman
Author-email: abdelrahman.rahal.mail@gmail.com
Requires-Python: >=3.10,<4.0
Classifier: Development Status :: 3 - Alpha
Classifier: Intended Audience :: Developers
Classifier: License :: OSI Approved :: MIT License
Classifier: Operating System :: OS Independent
Classifier: Programming Language :: Python :: 3
Classifier: Programming Language :: Python :: 3.10
Classifier: Programming Language :: Python :: 3.11
Requires-Dist: stackprinter (>=0.2.10)
Project-URL: Documentation, https://github.com/AbdelRahmanRahal/staticvar/blob/main/README.md
Project-URL: Repository, https://github.com/AbdelRahmanRahal/staticvar
